<?xml version="1.0" encoding="utf-8" ?>
<dwsync>
<file name="photo_001.jpg" server="alaa.site90.net/public_html/" local="127491026000000000" remote="129706449600000000" />
<file name="photo_002.jpg" server="alaa.site90.net/public_html/" local="127491010380000000" remote="129706449600000000" />
<file name="photo_003.jpg" server="alaa.site90.net/public_html/" local="127491010260000000" remote="129706449600000000" />
<file name="photo_004.jpg" server="alaa.site90.net/public_html/" local="127491002740000000" remote="129706449600000000" />
<file name="photo_005.jpg" server="alaa.site90.net/public_html/" local="127491002620000000" remote="129706449600000000" />
<file name="photo_006.jpg" server="alaa.site90.net/public_html/" local="127490992800000000" remote="129706449600000000" />
<file name="photo_007.jpg" server="alaa.site90.net/public_html/" local="128917326540000000" remote="129706449600000000" />
<file name="photo_008.jpg" server="alaa.site90.net/public_html/" local="127490977780000000" remote="129706449600000000" />
<file name="photo_009.jpg" server="alaa.site90.net/public_html/" local="128917328020000000" remote="129706449600000000" />
<file name="photo_010.jpg" server="alaa.site90.net/public_html/" local="128917327740000000" remote="129706449600000000" />
<file name="photo_011.jpg" server="alaa.site90.net/public_html/" local="128917327340000000" remote="129706449600000000" />
<file name="photo_012.jpg" server="alaa.site90.net/public_html/" local="129704479226441007" remote="129706449600000000" />
<file name="photo_013.jpg" server="alaa.site90.net/public_html/" local="127491067860000000" remote="129706449600000000" />
<file name="photo_014.jpg" server="alaa.site90.net/public_html/" local="127491067800000000" remote="129706450200000000" />
<file name="photo_015.jpg" server="alaa.site90.net/public_html/" local="127491067380000000" remote="129706450200000000" />
<file name="photo_016.jpg" server="alaa.site90.net/public_html/" local="127490978900000000" remote="129706450200000000" />
<file name="photo_017.jpg" server="alaa.site90.net/public_html/" local="127491067200000000" remote="129706450200000000" />
<file name="photo_018.jpg" server="alaa.site90.net/public_html/" local="127491067120000000" remote="129706450200000000" />
<file name="photo_019.jpg" server="alaa.site90.net/public_html/" local="127491066940000000" remote="129706450200000000" />
<file name="photo_020.jpg" server="alaa.site90.net/public_html/" local="127491066860000000" remote="129706450200000000" />
<file name="photo_021.jpg" server="alaa.site90.net/public_html/" local="127491040080000000" remote="129706450200000000" />
<file name="photo_022.jpg" server="alaa.site90.net/public_html/" local="127491035140000000" remote="129706450200000000" />
<file name="photo_023.jpg" server="alaa.site90.net/public_html/" local="127491034960000000" remote="129706450200000000" />
<file name="photo_024.jpg" server="alaa.site90.net/public_html/" local="127491028260000000" remote="129706450200000000" />
<file name="photo_025.jpg" server="alaa.site90.net/public_html/" local="127491027420000000" remote="129706450200000000" />
<file name="photo_026.jpg" server="alaa.site90.net/public_html/" local="127491026540000000" remote="129706450200000000" />
<file name="photo_027.jpg" server="alaa.site90.net/public_html/" local="127490978800000000" remote="129706450200000000" />
<file name="photo_028.jpg" server="alaa.site90.net/public_html/" local="127490977900000000" remote="129706450200000000" />
<file name="s_photo_001.jpg" server="alaa.site90.net/public_html/" local="127491026000000000" remote="129706450200000000" />
<file name="s_photo_002.jpg" server="alaa.site90.net/public_html/" local="127491010380000000" remote="129706450200000000" />
<file name="s_photo_003.jpg" server="alaa.site90.net/public_html/" local="127491010260000000" remote="129706450200000000" />
<file name="s_photo_004.jpg" server="alaa.site90.net/public_html/" local="127491002740000000" remote="129706450200000000" />
<file name="s_photo_005.jpg" server="alaa.site90.net/public_html/" local="127491002620000000" remote="129706450200000000" />
<file name="s_photo_006.jpg" server="alaa.site90.net/public_html/" local="127490992800000000" remote="129706450200000000" />
<file name="s_photo_007.jpg" server="alaa.site90.net/public_html/" local="128917326540000000" remote="129706450200000000" />
<file name="s_photo_008.jpg" server="alaa.site90.net/public_html/" local="127490977780000000" remote="129706450200000000" />
<file name="s_photo_010.jpg" server="alaa.site90.net/public_html/" local="128917327740000000" remote="129706450200000000" />
<file name="s_photo_011.jpg" server="alaa.site90.net/public_html/" local="128917327340000000" remote="129706450200000000" />
<file name="s_photo_012.jpg" server="alaa.site90.net/public_html/" local="129704479226441007" remote="129706450200000000" />
<file name="s_photo_013.jpg" server="alaa.site90.net/public_html/" local="127491067860000000" remote="129706450200000000" />
<file name="s_photo_014.jpg" server="alaa.site90.net/public_html/" local="127491067800000000" remote="129706450200000000" />
<file name="s_photo_015.jpg" server="alaa.site90.net/public_html/" local="127491067380000000" remote="129706450200000000" />
<file name="s_photo_016.jpg" server="alaa.site90.net/public_html/" local="127490978900000000" remote="129706450200000000" />
<file name="s_photo_017.jpg" server="alaa.site90.net/public_html/" local="127491067200000000" remote="129706450200000000" />
<file name="s_photo_018.jpg" server="alaa.site90.net/public_html/" local="127491067120000000" remote="129706450200000000" />
<file name="s_photo_019.jpg" server="alaa.site90.net/public_html/" local="127491066940000000" remote="129706450200000000" />
<file name="s_photo_020.jpg" server="alaa.site90.net/public_html/" local="127491066860000000" remote="129706450200000000" />
<file name="s_photo_021.jpg" server="alaa.site90.net/public_html/" local="127491040080000000" remote="129706450200000000" />
<file name="s_photo_022.jpg" server="alaa.site90.net/public_html/" local="127491035140000000" remote="129706450200000000" />
<file name="s_photo_023.jpg" server="alaa.site90.net/public_html/" local="127491034960000000" remote="129706450200000000" />
<file name="s_photo_024.jpg" server="alaa.site90.net/public_html/" local="127491028260000000" remote="129706450200000000" />
<file name="s_photo_025.jpg" server="alaa.site90.net/public_html/" local="127491027420000000" remote="129706450200000000" />
<file name="s_photo_026.jpg" server="alaa.site90.net/public_html/" local="127491026540000000" remote="129706450200000000" />
<file name="s_photo_027.jpg" server="alaa.site90.net/public_html/" local="127490978800000000" remote="129706450200000000" />
<file name="s_photo_028.jpg" server="alaa.site90.net/public_html/" local="127490977900000000" remote="129706450200000000" />
<file name="s_photo_009.jpg" server="alaa.site90.net/public_html/" local="128917328020000000" remote="129706450200000000" />
</dwsync>